<archimate:ArchimateDiagramModel
    xmlns:xsi="http://www.w3.org/2001/XMLSchema-instance"
    xmlns:archimate="http://www.archimatetool.com/archimate"
    name="Consultant AMOA"
    id="91510add">
  <children
      xsi:type="archimate:DiagramModelArchimateObject"
      id="80ec73aa">
    <sourceConnections
        xsi:type="archimate:DiagramModelArchimateConnection"
        id="3667fb0f"
        source="80ec73aa"
        target="b8c4b2f1">
      <archimateRelationship
          xsi:type="archimate:AssignmentRelationship"
          href="AssignmentRelationship_effb2460.xml#effb2460"/>
    </sourceConnections>
    <sourceConnections
        xsi:type="archimate:DiagramModelArchimateConnection"
        id="870ca798"
        source="80ec73aa"
        target="482b1a13">
      <archimateRelationship
          xsi:type="archimate:AssignmentRelationship"
          href="AssignmentRelationship_a879ebd8.xml#a879ebd8"/>
    </sourceConnections>
    <sourceConnections
        xsi:type="archimate:DiagramModelArchimateConnection"
        id="20bf3bed"
        source="80ec73aa"
        target="6a4f5e95">
      <archimateRelationship
          xsi:type="archimate:AssignmentRelationship"
          href="AssignmentRelationship_0f4cb548.xml#0f4cb548"/>
    </sourceConnections>
    <bounds
        x="408"
        y="240"
        width="120"
        height="55"/>
    <archimateElement
        xsi:type="archimate:BusinessActor"
        href="BusinessActor_4711df9a.xml#4711df9a"/>
  </children>
  <children
      xsi:type="archimate:DiagramModelArchimateObject"
      id="b8c4b2f1"
      targetConnections="3667fb0f">
    <sourceConnections
        xsi:type="archimate:DiagramModelArchimateConnection"
        id="055e36ea"
        source="b8c4b2f1"
        target="f7f74316">
      <archimateRelationship
          xsi:type="archimate:AggregationRelationship"
          href="AggregationRelationship_bfe1ff41.xml#bfe1ff41"/>
    </sourceConnections>
    <sourceConnections
        xsi:type="archimate:DiagramModelArchimateConnection"
        id="f962e4fd"
        source="b8c4b2f1"
        target="e305bf37">
      <archimateRelationship
          xsi:type="archimate:AggregationRelationship"
          href="AggregationRelationship_e23953e4.xml#e23953e4"/>
    </sourceConnections>
    <bounds
        x="708"
        y="43"
        width="457"
        height="377"/>
    <children
        xsi:type="archimate:DiagramModelArchimateObject"
        id="e305bf37"
        targetConnections="f962e4fd">
      <bounds
          x="24"
          y="120"
          width="396"
          height="55"/>
      <archimateElement
          xsi:type="archimate:BusinessRole"
          href="BusinessRole_e889506c.xml#e889506c"/>
    </children>
    <children
        xsi:type="archimate:DiagramModelArchimateObject"
        id="f7f74316"
        targetConnections="055e36ea">
      <bounds
          x="24"
          y="25"
          width="396"
          height="84"/>
      <archimateElement
          xsi:type="archimate:BusinessRole"
          href="BusinessRole_177483cc.xml#177483cc"/>
    </children>
    <children
        xsi:type="archimate:DiagramModelArchimateObject"
        id="506fe4a1">
      <bounds
          x="24"
          y="180"
          width="396"
          height="55"/>
      <archimateElement
          xsi:type="archimate:BusinessRole"
          href="BusinessRole_125a0845.xml#125a0845"/>
    </children>
    <children
        xsi:type="archimate:DiagramModelArchimateObject"
        id="0fb456b2">
      <bounds
          x="24"
          y="244"
          width="396"
          height="55"/>
      <archimateElement
          xsi:type="archimate:BusinessRole"
          href="BusinessRole_a4b9d752.xml#a4b9d752"/>
    </children>
    <children
        xsi:type="archimate:DiagramModelArchimateObject"
        id="18393635">
      <bounds
          x="24"
          y="312"
          width="396"
          height="55"/>
      <archimateElement
          xsi:type="archimate:BusinessRole"
          href="BusinessRole_b9056694.xml#b9056694"/>
    </children>
    <archimateElement
        xsi:type="archimate:BusinessRole"
        href="BusinessRole_b55ad4b7.xml#b55ad4b7"/>
  </children>
  <children
      xsi:type="archimate:DiagramModelArchimateObject"
      id="6a4f5e95"
      targetConnections="20bf3bed">
    <bounds
        x="36"
        y="234"
        width="313"
        height="186"/>
    <children
        xsi:type="archimate:DiagramModelArchimateObject"
        id="34f0b52e">
      <bounds
          x="12"
          y="84"
          width="201"
          height="55"/>
      <archimateElement
          xsi:type="archimate:BusinessProcess"
          href="BusinessProcess_f6fd4571.xml#f6fd4571"/>
    </children>
    <children
        xsi:type="archimate:DiagramModelArchimateObject"
        id="83919856">
      <bounds
          x="12"
          y="24"
          width="201"
          height="55"/>
      <archimateElement
          xsi:type="archimate:BusinessProcess"
          href="BusinessProcess_5aa03c8f.xml#5aa03c8f"/>
    </children>
    <archimateElement
        xsi:type="archimate:BusinessProcess"
        href="BusinessProcess_a30459ac.xml#a30459ac"/>
  </children>
  <children
      xsi:type="archimate:DiagramModelArchimateObject"
      id="482b1a13"
      targetConnections="870ca798">
    <bounds
        x="624"
        y="492"
        width="289"
        height="55"/>
    <archimateElement
        xsi:type="archimate:BusinessFunction"
        href="BusinessFunction_4e4a4fb9.xml#4e4a4fb9"/>
  </children>
</archimate:ArchimateDiagramModel>
